{"assets/audio/My-Little-Queen.mp3":["assets/audio/My-Little-Queen.mp3"],"assets/fonts/DiloWorld-mLJLv.ttf":["assets/fonts/DiloWorld-mLJLv.ttf"],"assets/pics/0.png":["assets/pics/0.png"],"assets/pics/1.png":["assets/pics/1.png"],"assets/pics/2.png":["assets/pics/2.png"],"assets/pics/bird.png":["assets/pics/bird.png"],"assets/pics/blue.png":["assets/pics/blue.png"],"assets/pics/green.png":["assets/pics/green.png"],"assets/pics/icon.jpg":["assets/pics/icon.jpg"],"assets/pics/loss.json":["assets/pics/loss.json"],"assets/pics/starla.png":["assets/pics/starla.png"],"assets/pics/starla2.png":["assets/pics/starla2.png"],"assets/pics/starla3.png":["assets/pics/starla3.png"],"assets/pics/starlaz.png":["assets/pics/starlaz.png"],"packages/cupertino_icons/assets/CupertinoIcons.ttf":["packages/cupertino_icons/assets/CupertinoIcons.ttf"]}